[
  {
    "homeTeam": "Talleres",
    "homeTeamImg": "https://api.promiedos.com.ar/images/team/jche/1",
    "awayTeam": "Instituto",
    "awayTeamImg": "https://api.promiedos.com.ar/images/team/hchc/1",
    "date": "14:00",
    "score": "",
    "round": 16
  },
  {
    "homeTeam": "Gimnasia",
    "homeTeamImg": "https://api.promiedos.com.ar/images/team/iia/1",
    "awayTeam": "Platense",
    "awayTeamImg": "https://api.promiedos.com.ar/images/team/hcah/1",
    "date": "14:00",
    "score": "",
    "round": 16
  },
  {
    "homeTeam": "River",
    "homeTeamImg": "https://api.promiedos.com.ar/images/team/igi/1",
    "awayTeam": "Vélez",
    "awayTeamImg": "https://api.promiedos.com.ar/images/team/ihc/1",
    "date": "14:00",
    "score": "",
    "round": 16
  },
  {
    "homeTeam": "Central",
    "homeTeamImg": "https://api.promiedos.com.ar/images/team/ihf/1",
    "awayTeam": "Independiente",
    "awayTeamImg": "https://api.promiedos.com.ar/images/team/ihe/1",
    "date": "14:00",
    "score": "",
    "round": 16
  },
  {
    "homeTeam": "Sarmiento",
    "homeTeamImg": "https://api.promiedos.com.ar/images/team/hbbh/1",
    "awayTeam": "San Lorenzo",
    "awayTeamImg": "https://api.promiedos.com.ar/images/team/igf/1",
    "date": "14:00",
    "score": "",
    "round": 16
  },
  {
    "homeTeam": "Riestra",
    "homeTeamImg": "https://api.promiedos.com.ar/images/team/bbjea/1",
    "awayTeam": "Godoy Cruz",
    "awayTeamImg": "https://api.promiedos.com.ar/images/team/ihd/1",
    "date": "14:00",
    "score": "",
    "round": 16
  },
  {
    "homeTeam": "Atl. Tucumán",
    "homeTeamImg": "https://api.promiedos.com.ar/images/team/gbfc/1",
    "awayTeam": "Lanús",
    "awayTeamImg": "https://api.promiedos.com.ar/images/team/igj/1",
    "date": "14:00",
    "score": "",
    "round": 16
  },
  {
    "homeTeam": "Tigre",
    "homeTeamImg": "https://api.promiedos.com.ar/images/team/iid/1",
    "awayTeam": "Boca Jrs.",
    "awayTeamImg": "https://api.promiedos.com.ar/images/team/igg/1",
    "date": "14:00",
    "score": "",
    "round": 16
  },
  {
    "homeTeam": "Argentinos",
    "homeTeamImg": "https://api.promiedos.com.ar/images/team/ihb/1",
    "awayTeam": "Estudiantes",
    "awayTeamImg": "https://api.promiedos.com.ar/images/team/igh/1",
    "date": "14:00",
    "score": "",
    "round": 16
  },
  {
    "homeTeam": "Unión",
    "homeTeamImg": "https://api.promiedos.com.ar/images/team/hcag/1",
    "awayTeam": "Belgrano",
    "awayTeamImg": "https://api.promiedos.com.ar/images/team/fhid/1",
    "date": "14:00",
    "score": "",
    "round": 16
  },
  {
    "homeTeam": "Huracán",
    "homeTeamImg": "https://api.promiedos.com.ar/images/team/iie/1",
    "awayTeam": "Barracas",
    "awayTeamImg": "https://api.promiedos.com.ar/images/team/jafb/1",
    "date": "14:00",
    "score": "",
    "round": 16
  },
  {
    "homeTeam": "Racing",
    "homeTeamImg": "https://api.promiedos.com.ar/images/team/ihg/1",
    "awayTeam": "Newell's",
    "awayTeamImg": "https://api.promiedos.com.ar/images/team/ihh/1",
    "date": "14:00",
    "score": "",
    "round": 16
  },
  {
    "homeTeam": "Ind. Rivadavia",
    "homeTeamImg": "https://api.promiedos.com.ar/images/team/hcch/1",
    "awayTeam": "Defensa",
    "awayTeamImg": "https://api.promiedos.com.ar/images/team/hcbh/1",
    "date": "14:00",
    "score": "",
    "round": 16
  },
  {
    "homeTeam": "Banfield",
    "homeTeamImg": "https://api.promiedos.com.ar/images/team/ihi/1",
    "awayTeam": "Central Córdoba",
    "awayTeamImg": "https://api.promiedos.com.ar/images/team/beafh/1",
    "date": "14:00",
    "score": "",
    "round": 16
  },
  {
    "homeTeam": "San Martín",
    "homeTeamImg": "https://api.promiedos.com.ar/images/team/hcai/1",
    "awayTeam": "Aldosivi",
    "awayTeamImg": "https://api.promiedos.com.ar/images/team/hccd/1",
    "date": "14:00",
    "score": "",
    "round": 16
  }
]